todov1/__init__.py
todov1/todov1.py
todov2/__init__.py
todov2/todo.py
todov3/__init__.py
todov3/todo.py
rkt_cli_test_101-0.0.1.dist-info/METADATA
rkt_cli_test_101-0.0.1.dist-info/WHEEL
rkt_cli_test_101-0.0.1.dist-info/entry_points.txt
rkt_cli_test_101-0.0.1.dist-info/top_level.txt
rkt_cli_test_101-0.0.1.dist-info/RECORD
